{
    "overrides": [
          {
            "predicate": {
              "nbt": {
                "VB|Protocol1_18_2To1_19|id": 710
              }
            },
            "model": "item/mangrove_boat"
          },
          {
              "predicate": {
                "nbt": {
                  "VB|Protocol1_18_2To1_19|id": 711
                }
              },
              "model": "item/mangrove_chest_boat"
          },
          {
              "predicate": {
                "nbt": {
                  "VB|Protocol1_18_2To1_19|id": 707
                }
              },
              "model": "item/acacia_chest_boat"
          },
          {
              "predicate": {
                "nbt": {
                  "VB|Protocol1_19_3To1_19_4|id": 742
                }
              },
              "model": "item/cherry_boat"
          },
          {
              "predicate": {
                "nbt": {
                  "VB|Protocol1_19_3To1_19_4|id": 743
                }
              },
              "model": "item/cherry_chest_boat"
          }
      ]
  }