{
    "overrides": [
        {
          "predicate": {
            "nbt": {
              "VB|Protocol1_19_3To1_19_1|id": 828
            }
          },
          "model": "item/bamboo_sign"
        },
        {
          "predicate": {
            "nbt": {
              "VB|Protocol1_19_3To1_19_1|id": 831
            }
          },
          "model": "item/oak_hanging_sign"
        },
        {
          "predicate": {
            "nbt": {
              "VB|Protocol1_19_3To1_19_1|id": 833
            }
          },
          "model": "item/birch_hanging_sign"
        },
        {
          "predicate": {
            "nbt": {
              "VB|Protocol1_19_3To1_19_1|id": 838
            }
          },
          "model": "item/bamboo_hanging_sign"
        }
    ]
}