{
    "overrides": [
        {
          "predicate": {
            "nbt":{
              "VB|Protocol1_16_4To1_17|id": 342
            }
          },
          "model": "item/cobbled_deepslate_wall"
        },
        {
          "predicate": {
            "nbt":{
              "VB|Protocol1_16_4To1_17|id": 345
            }
          },
          "model": "item/deepslate_tile_wall"
        },
        {
          "predicate": {
            "nbt":{
              "VB|Protocol1_16_4To1_17|id": 343
            }
          },
          "model": "item/polished_deepslate_wall"
        }
    ]
}